MANIFEST.in
README.rst
setup.py
tradegecko/__init__.py
tradegecko/api.py
tradegecko/endpoints.py
tradegecko_python.egg-info/PKG-INFO
tradegecko_python.egg-info/SOURCES.txt
tradegecko_python.egg-info/dependency_links.txt
tradegecko_python.egg-info/pbr.json
tradegecko_python.egg-info/requires.txt
tradegecko_python.egg-info/top_level.txt