Metadata-Version: 1.0
Name: tradegecko-python
Version: 0.0.7
Summary: Python wrapper for TradeGecko REST API
Home-page: https://github.com/epantry/tradegecko-python
Author: Drew Kowalik, Chris Clark
Author-email: team@epantry.com
License: UNKNOWN
Keywords: tradegecko
Platform: UNKNOWN
